QianyiDaoYunYuanshengYingyongJiagou/README.md
QianyiDaoYunYuanshengYingyongJiagou/__init__.py
QianyiDaoYunYuanshengYingyongJiagou/__main__.py
QianyiDaoYunYuanshengYingyongJiagou/file.epub
QianyiDaoYunYuanshengYingyongJiagou/index.html
QianyiDaoYunYuanshengYingyongJiagou/css/__init__.py
QianyiDaoYunYuanshengYingyongJiagou/css/annotations.css
QianyiDaoYunYuanshengYingyongJiagou/css/main.css
QianyiDaoYunYuanshengYingyongJiagou/css/normalize.css
QianyiDaoYunYuanshengYingyongJiagou/css/popup.css
QianyiDaoYunYuanshengYingyongJiagou/font/__init__.py
QianyiDaoYunYuanshengYingyongJiagou/font/fontello.eot
QianyiDaoYunYuanshengYingyongJiagou/font/fontello.svg
QianyiDaoYunYuanshengYingyongJiagou/font/fontello.ttf
QianyiDaoYunYuanshengYingyongJiagou/font/fontello.woff
QianyiDaoYunYuanshengYingyongJiagou/img/__init__.py
QianyiDaoYunYuanshengYingyongJiagou/img/annotator-glyph-sprite.png
QianyiDaoYunYuanshengYingyongJiagou/img/annotator-icon-sprite.png
QianyiDaoYunYuanshengYingyongJiagou/img/apple-touch-icon.png
QianyiDaoYunYuanshengYingyongJiagou/img/cancelfullscreen.png
QianyiDaoYunYuanshengYingyongJiagou/img/close.png
QianyiDaoYunYuanshengYingyongJiagou/img/fullscreen.png
QianyiDaoYunYuanshengYingyongJiagou/img/loader.gif
QianyiDaoYunYuanshengYingyongJiagou/img/menu-icon.png
QianyiDaoYunYuanshengYingyongJiagou/img/save.png
QianyiDaoYunYuanshengYingyongJiagou/img/saved.png
QianyiDaoYunYuanshengYingyongJiagou/img/settings-s.png
QianyiDaoYunYuanshengYingyongJiagou/img/settings.png
QianyiDaoYunYuanshengYingyongJiagou/img/star.png
QianyiDaoYunYuanshengYingyongJiagou/js/__init__.py
QianyiDaoYunYuanshengYingyongJiagou/js/epub.js
QianyiDaoYunYuanshengYingyongJiagou/js/epub.min.js
QianyiDaoYunYuanshengYingyongJiagou/js/epub.min.map
QianyiDaoYunYuanshengYingyongJiagou/js/hooks.min.js
QianyiDaoYunYuanshengYingyongJiagou/js/hooks.min.map
QianyiDaoYunYuanshengYingyongJiagou/js/reader.js
QianyiDaoYunYuanshengYingyongJiagou/js/reader.js.map
QianyiDaoYunYuanshengYingyongJiagou/js/reader.min.js
qianyi_dao_yun_yuansheng_yingyong_jiagou-2024.3.4.0.dist-info/METADATA
qianyi_dao_yun_yuansheng_yingyong_jiagou-2024.3.4.0.dist-info/WHEEL
qianyi_dao_yun_yuansheng_yingyong_jiagou-2024.3.4.0.dist-info/entry_points.txt
qianyi_dao_yun_yuansheng_yingyong_jiagou-2024.3.4.0.dist-info/top_level.txt
qianyi_dao_yun_yuansheng_yingyong_jiagou-2024.3.4.0.dist-info/RECORD
